README.md
setup.py
fuo_local/__init__.py
fuo_local/consts.py
fuo_local/db.py
fuo_local/lans_helpers.py
fuo_local/models.py
fuo_local/patch.py
fuo_local/provider.py
fuo_local/scanner.py
fuo_local/schemas.py
fuo_local/ui.py
fuo_local/utils.py
fuo_local.egg-info/PKG-INFO
fuo_local.egg-info/SOURCES.txt
fuo_local.egg-info/dependency_links.txt
fuo_local.egg-info/entry_points.txt
fuo_local.egg-info/requires.txt
fuo_local.egg-info/top_level.txt