Metadata-Version: 2.1
Name: fuo-local
Version: 0.3
Summary: feeluown local plugin
Home-page: https://github.com/feeluown/feeluown-local
Author: Cosven
Author-email: yinshaowen241@gmail.com
License: UNKNOWN
Keywords: feeluown,plugin,local
Platform: UNKNOWN
Classifier: Development Status :: 3 - Alpha
Classifier: Programming Language :: Python :: 3.5
Classifier: Programming Language :: Python :: 3.6
Classifier: Programming Language :: Python :: 3.7
Classifier: Programming Language :: Python :: 3 :: Only
